src/__init__.py
src/cli.py
gitreport-0.0.6.dist-info/METADATA
gitreport-0.0.6.dist-info/WHEEL
gitreport-0.0.6.dist-info/entry_points.txt
gitreport-0.0.6.dist-info/top_level.txt
gitreport-0.0.6.dist-info/RECORD
