Metadata-Version: 2.1
Name: gitreport
Version: 0.0.6
Summary: Productivity git report to avoid stupid job in every month
Home-page: https://github.com/peelz/git-report
Author: monopeelz
Author-email: monopeelz@gmail.com
License: UNKNOWN
Project-URL: Bug Tracker, https://github.com/peelz/git-report/issues
Platform: UNKNOWN
Classifier: Programming Language :: Python :: 3
Classifier: License :: OSI Approved :: MIT License
Classifier: Operating System :: OS Independent
Requires-Python: >=3.6
Requires-Dist: GitPython
Requires-Dist: XlsxWriter (~=1.4.3)
